id_penerator_pkg/__init__.py
id_penerator_pkg/id_properties.py
id_penerator_pkg-0.0.1.dist-info/LICENSE
id_penerator_pkg-0.0.1.dist-info/METADATA
id_penerator_pkg-0.0.1.dist-info/WHEEL
id_penerator_pkg-0.0.1.dist-info/top_level.txt
id_penerator_pkg-0.0.1.dist-info/RECORD
