Metadata-Version: 2.1
Name: id_penerator_pkg
Version: 0.0.1
Summary: Creating contract id using date and email
Home-page: https://github.com/Myungjee-koh/cpp_library.git
Author: Myungjee Koh
Author-email: x23268409@student.ncirl.ie
Classifier: Programming Language :: Python :: 3
Classifier: License :: OSI Approved :: MIT License
Classifier: Operating System :: OS Independent
Requires-Python: >=3.6
License-File: LICENSE
